dateparser-stubs/METADATA.toml
dateparser-stubs/__init__.pyi
dateparser-stubs/conf.pyi
dateparser-stubs/date.pyi
dateparser-stubs/date_parser.pyi
dateparser-stubs/freshness_date_parser.pyi
dateparser-stubs/parser.pyi
dateparser-stubs/py.typed
dateparser-stubs/timezone_parser.pyi
dateparser-stubs/timezones.pyi
dateparser-stubs/calendars/__init__.pyi
dateparser-stubs/calendars/hijri.pyi
dateparser-stubs/calendars/hijri_parser.pyi
dateparser-stubs/calendars/jalali.pyi
dateparser-stubs/calendars/jalali_parser.pyi
dateparser-stubs/custom_language_detection/__init__.pyi
dateparser-stubs/custom_language_detection/fasttext.pyi
dateparser-stubs/custom_language_detection/langdetect.pyi
dateparser-stubs/custom_language_detection/language_mapping.pyi
dateparser-stubs/data/__init__.pyi
dateparser-stubs/data/languages_info.pyi
dateparser-stubs/languages/__init__.pyi
dateparser-stubs/languages/dictionary.pyi
dateparser-stubs/languages/loader.pyi
dateparser-stubs/languages/locale.pyi
dateparser-stubs/languages/validation.pyi
dateparser-stubs/search/__init__.pyi
dateparser-stubs/search/detection.pyi
dateparser-stubs/search/search.pyi
dateparser-stubs/search/text_detection.pyi
dateparser-stubs/utils/__init__.pyi
dateparser-stubs/utils/strptime.pyi
dateparser_data-stubs/METADATA.toml
dateparser_data-stubs/__init__.pyi
dateparser_data-stubs/py.typed
dateparser_data-stubs/settings.pyi
types_dateparser-1.2.2.20250627.dist-info/licenses/LICENSE
types_dateparser-1.2.2.20250627.dist-info/METADATA
types_dateparser-1.2.2.20250627.dist-info/WHEEL
types_dateparser-1.2.2.20250627.dist-info/top_level.txt
types_dateparser-1.2.2.20250627.dist-info/RECORD
